{
	"name": "df_agencydata",
	"properties": {
		"type": "MappingDataFlow",
		"typeProperties": {
			"sources": [
				{
					"dataset": {
						"referenceName": "DS_AgencyMaster",
						"type": "DatasetReference"
					},
					"name": "agencycsv"
				}
			],
			"sinks": [
				{
					"name": "sink1"
				}
			],
			"transformations": [],
			"scriptLines": [
				"source(output(",
				"          AgencyID as string,",
				"          AgencyName as string",
				"     ),",
				"     allowSchemaDrift: true,",
				"     validateSchema: false,",
				"     ignoreNoFilesFound: false) ~> agencycsv",
				"agencycsv sink(allowSchemaDrift: true,",
				"     validateSchema: false,",
				"     skipDuplicateMapInputs: true,",
				"     skipDuplicateMapOutputs: true) ~> sink1"
			]
		}
	}
}